hangulpy/__init__.py
hangulpy/chosung.py
hangulpy/hangul_assemble.py
hangulpy/hangul_check.py
hangulpy/hangul_contains.py
hangulpy/hangul_decompose.py
hangulpy/hangul_ends_with_consonant.py
hangulpy/hangul_number.py
hangulpy/hangul_properties.py
hangulpy/hangul_role.py
hangulpy/hangul_sort.py
hangulpy/hangul_split.py
hangulpy/hangul_syllable.py
hangulpy/hangul_typoerror.py
hangulpy/is_hangul.py
hangulpy/josa.py
hangulpy/match_hangul_pattern.py
hangulpy/noun.py
hangulpy/py.typed
hangulpy/romanize.py
hangulpy/utils.py
hangulpy-1.3.0.dist-info/licenses/LICENSE
hangulpy-1.3.0.dist-info/METADATA
hangulpy-1.3.0.dist-info/WHEEL
hangulpy-1.3.0.dist-info/top_level.txt
hangulpy-1.3.0.dist-info/RECORD
