Metadata-Version: 2.4
Name: hangulpy
Version: 1.3.0
Summary: A comprehensive Python library for Korean language processing, inspired by es-hangul
Home-page: https://github.com/gaon12/hangulpy
Author: Jeong Gaon
Author-email: Jeong Gaon <gokirito12@gmail.com>
Maintainer-email: Jeong Gaon <gokirito12@gmail.com>
License: MIT
Project-URL: Homepage, https://github.com/gaon12/hangulpy
Project-URL: Documentation, https://wiki.uiharu.dev/w/hangulpy
Project-URL: Repository, https://github.com/gaon12/hangulpy
Project-URL: Bug Tracker, https://github.com/gaon12/hangulpy/issues
Project-URL: Changelog, https://github.com/gaon12/hangulpy/releases
Keywords: korean,hangul,josa,particle,chosung,romanization,korean-language,nlp,text-processing
Classifier: Development Status :: 4 - Beta
Classifier: Intended Audience :: Developers
Classifier: License :: OSI Approved :: MIT License
Classifier: Operating System :: OS Independent
Classifier: Programming Language :: Python :: 3
Classifier: Programming Language :: Python :: 3.8
Classifier: Programming Language :: Python :: 3.9
Classifier: Programming Language :: Python :: 3.10
Classifier: Programming Language :: Python :: 3.11
Classifier: Programming Language :: Python :: 3.12
Classifier: Programming Language :: Python :: 3.13
Classifier: Topic :: Software Development :: Libraries :: Python Modules
Classifier: Topic :: Text Processing :: Linguistic
Requires-Python: >=3.8
License-File: LICENSE
Provides-Extra: dev
Requires-Dist: pytest>=7.4.0; extra == "dev"
Requires-Dist: pytest-cov>=4.1.0; extra == "dev"
Requires-Dist: black>=23.0.0; extra == "dev"
Requires-Dist: ruff>=0.1.0; extra == "dev"
Requires-Dist: mypy>=1.5.0; extra == "dev"
Provides-Extra: test
Requires-Dist: pytest>=7.4.0; extra == "test"
Requires-Dist: pytest-cov>=4.1.0; extra == "test"
Provides-Extra: lint
Requires-Dist: black>=23.0.0; extra == "lint"
Requires-Dist: ruff>=0.1.0; extra == "lint"
Requires-Dist: mypy>=1.5.0; extra == "lint"
Dynamic: author
Dynamic: home-page
Dynamic: license-file
Dynamic: requires-python
